esipy/__init__.py
esipy/atomicfiles.py
esipy/indicators.py
esipy/make_aoms.py
esipy/no.py
esipy/rest.py
esipy/tools.py
esipy/unrest.py
esipython-1.0.6.data/scripts/aom2esi
esipython-1.0.6.data/scripts/int2esi
esipython-1.0.6.dist-info/licenses/LICENSE
esipython-1.0.6.dist-info/METADATA
esipython-1.0.6.dist-info/WHEEL
esipython-1.0.6.dist-info/top_level.txt
esipython-1.0.6.dist-info/RECORD
