Metadata-Version: 2.4
Name: esipython
Version: 1.0.6
Summary: Calculation of electronic aromaticity indicators
Home-page: https://github.com/jgrebol/ESIpy
Author: Joan Grebol, Eduard Matito, Pedro Salvador
License-File: LICENSE
Requires-Dist: numpy<=1.23.3
Requires-Dist: pyscf<=2.4
Requires-Dist: sphinx
Dynamic: author
Dynamic: description
Dynamic: description-content-type
Dynamic: home-page
Dynamic: license-file
Dynamic: requires-dist
Dynamic: summary
